bicidata
