Metadata-Version: 2.1
Name: bicidata
Version: 0.0.4
Summary: bicidata is a framework to work with the General Bikeshare Feed Specification (GBFS)
Home-page: https://github.com/bicidata/bicidata
Author: Ismael Benito Altamirano
Author-email: 
License: UNKNOWN
Platform: UNKNOWN
